pyLSV2/__init__.py
pyLSV2/client.py
pyLSV2/const.py
pyLSV2/dat_cls.py
pyLSV2/err.py
pyLSV2/low_level_com.py
pyLSV2/misc.py
pyLSV2/misc_scope.py
pyLSV2/table_reader.py
pyLSV2/translate_messages.py
pyLSV2/locales/de/LC_MESSAGES/error_text.po
pyLSV2/locales/de/LC_MESSAGES/message_text.po
pyLSV2/locales/en/LC_MESSAGES/error_text.po
pyLSV2/locales/en/LC_MESSAGES/message_text.po
pyLSV2/scripts/__init__.py
pyLSV2/scripts/cmd.py
pyLSV2/scripts/demo.py
pyLSV2/scripts/scope2csv.py
pyLSV2/scripts/ssh_tunnel.py
pyLSV2/scripts/tab2csv.py
pylsv2-1.5.dist-info/licenses/LICENSE
pylsv2-1.5.dist-info/METADATA
pylsv2-1.5.dist-info/WHEEL
pylsv2-1.5.dist-info/entry_points.txt
pylsv2-1.5.dist-info/top_level.txt
pylsv2-1.5.dist-info/RECORD
