Metadata-Version: 2.4
Name: pyLSV2
Version: 1.5
Summary: A pure Python3 implementation of the LSV2 protocol
Author-email: drunsinn <dr.unsinn@googlemail.com>
License: MIT License
Project-URL: Homepage, https://github.com/drunsinn/pyLSV2
Project-URL: Bug Tracker, https://github.com/drunsinn/pyLSV2/issues
Keywords: LSV2,CNC,PLC
Requires-Python: >=3.6
License-File: LICENSE
Provides-Extra: ssh
Requires-Dist: sshtunnel>=0.4; extra == "ssh"
Dynamic: license-file
